{
  "Table1": [
    {
      "DECLARATION_ID": 1042840
    },
    {
      "DECLARATION_ID": 1042844
    },
    {
      "DECLARATION_ID": 1042860
    },
    {
      "DECLARATION_ID": 1042898
    },
    {
      "DECLARATION_ID": 1042902
    },
    {
      "DECLARATION_ID": 1045140
    },
    {
      "DECLARATION_ID": 1045198
    },
    {
      "DECLARATION_ID": 1045205
    },
    {
      "DECLARATION_ID": 1045210
    },
    {
      "DECLARATION_ID": 1045214
    },
    {
      "DECLARATION_ID": 1045220
    },
    {
      "DECLARATION_ID": 1045223
    },
    {
      "DECLARATION_ID": 1057854
    },
    {
      "DECLARATION_ID": 1057923
    },
    {
      "DECLARATION_ID": 1070903
    },
    {
      "DECLARATION_ID": 1075647
    },
    {
      "DECLARATION_ID": 1077506
    },
    {
      "DECLARATION_ID": 1079355
    },
    {
      "DECLARATION_ID": 1079677
    },
    {
      "DECLARATION_ID": 1085531
    },
    {
      "DECLARATION_ID": 1086536
    },
    {
      "DECLARATION_ID": 1087235
    },
    {
      "DECLARATION_ID": 1087239
    },
    {
      "DECLARATION_ID": 1088043
    },
    {
      "DECLARATION_ID": 1095218
    },
    {
      "DECLARATION_ID": 1099143
    },
    {
      "DECLARATION_ID": 1099344
    },
    {
      "DECLARATION_ID": 1099546
    },
    {
      "DECLARATION_ID": 1099551
    },
    {
      "DECLARATION_ID": 1100481
    },
    {
      "DECLARATION_ID": 1101847
    },
    {
      "DECLARATION_ID": 1102644
    },
    {
      "DECLARATION_ID": 1106856
    },
    {
      "DECLARATION_ID": 1118857
    },
    {
      "DECLARATION_ID": 1123107
    },
    {
      "DECLARATION_ID": 1152626
    },
    {
      "DECLARATION_ID": 1152636
    },
    {
      "DECLARATION_ID": 1154033
    },
    {
      "DECLARATION_ID": 1154036
    },
    {
      "DECLARATION_ID": 1154038
    },
    {
      "DECLARATION_ID": 1154997
    },
    {
      "DECLARATION_ID": 1155000
    },
    {
      "DECLARATION_ID": 1156749
    },
    {
      "DECLARATION_ID": 1161806
    },
    {
      "DECLARATION_ID": 1164574
    },
    {
      "DECLARATION_ID": 1167731
    },
    {
      "DECLARATION_ID": 1176698
    },
    {
      "DECLARATION_ID": 1176699
    },
    {
      "DECLARATION_ID": 1180918
    },
    {
      "DECLARATION_ID": 1182399
    },
    {
      "DECLARATION_ID": 1183520
    },
    {
      "DECLARATION_ID": 1184372
    },
    {
      "DECLARATION_ID": 1188766
    },
    {
      "DECLARATION_ID": 1188773
    },
    {
      "DECLARATION_ID": 1194150
    },
    {
      "DECLARATION_ID": 1194528
    },
    {
      "DECLARATION_ID": 1194582
    },
    {
      "DECLARATION_ID": 1194583
    },
    {
      "DECLARATION_ID": 1194584
    },
    {
      "DECLARATION_ID": 1194671
    },
    {
      "DECLARATION_ID": 1195828
    },
    {
      "DECLARATION_ID": 1202218
    },
    {
      "DECLARATION_ID": 1202751
    },
    {
      "DECLARATION_ID": 1202753
    },
    {
      "DECLARATION_ID": 1202826
    },
    {
      "DECLARATION_ID": 1202829
    },
    {
      "DECLARATION_ID": 1203264
    },
    {
      "DECLARATION_ID": 1203644
    },
    {
      "DECLARATION_ID": 1203688
    },
    {
      "DECLARATION_ID": 1203689
    },
    {
      "DECLARATION_ID": 1203690
    },
    {
      "DECLARATION_ID": 1203692
    },
    {
      "DECLARATION_ID": 1203693
    },
    {
      "DECLARATION_ID": 1203694
    },
    {
      "DECLARATION_ID": 1203968
    },
    {
      "DECLARATION_ID": 1203969
    },
    {
      "DECLARATION_ID": 1203970
    },
    {
      "DECLARATION_ID": 1204063
    },
    {
      "DECLARATION_ID": 1204096
    },
    {
      "DECLARATION_ID": 1204099
    },
    {
      "DECLARATION_ID": 1204100
    },
    {
      "DECLARATION_ID": 1204101
    },
    {
      "DECLARATION_ID": 1204130
    },
    {
      "DECLARATION_ID": 1204131
    },
    {
      "DECLARATION_ID": 1204147
    },
    {
      "DECLARATION_ID": 1204171
    },
    {
      "DECLARATION_ID": 1204172
    },
    {
      "DECLARATION_ID": 1204173
    },
    {
      "DECLARATION_ID": 1204174
    },
    {
      "DECLARATION_ID": 1204318
    },
    {
      "DECLARATION_ID": 1204352
    },
    {
      "DECLARATION_ID": 1204353
    },
    {
      "DECLARATION_ID": 1204437
    },
    {
      "DECLARATION_ID": 1204439
    },
    {
      "DECLARATION_ID": 1204464
    },
    {
      "DECLARATION_ID": 1204479
    },
    {
      "DECLARATION_ID": 1204642
    },
    {
      "DECLARATION_ID": 1204700
    },
    {
      "DECLARATION_ID": 1204701
    },
    {
      "DECLARATION_ID": 1204703
    },
    {
      "DECLARATION_ID": 1204705
    },
    {
      "DECLARATION_ID": 1204706
    },
    {
      "DECLARATION_ID": 1204707
    },
    {
      "DECLARATION_ID": 1204708
    },
    {
      "DECLARATION_ID": 1204709
    },
    {
      "DECLARATION_ID": 1204710
    },
    {
      "DECLARATION_ID": 1204711
    },
    {
      "DECLARATION_ID": 1204712
    },
    {
      "DECLARATION_ID": 1204718
    },
    {
      "DECLARATION_ID": 1204720
    },
    {
      "DECLARATION_ID": 1204723
    },
    {
      "DECLARATION_ID": 1204789
    },
    {
      "DECLARATION_ID": 1204792
    },
    {
      "DECLARATION_ID": 1204793
    },
    {
      "DECLARATION_ID": 1204804
    },
    {
      "DECLARATION_ID": 1204805
    },
    {
      "DECLARATION_ID": 1204807
    },
    {
      "DECLARATION_ID": 1204808
    },
    {
      "DECLARATION_ID": 1204809
    },
    {
      "DECLARATION_ID": 1204810
    },
    {
      "DECLARATION_ID": 1204875
    },
    {
      "DECLARATION_ID": 1204876
    },
    {
      "DECLARATION_ID": 1204890
    },
    {
      "DECLARATION_ID": 1204891
    },
    {
      "DECLARATION_ID": 1204892
    },
    {
      "DECLARATION_ID": 1204893
    },
    {
      "DECLARATION_ID": 1204894
    },
    {
      "DECLARATION_ID": 1204977
    },
    {
      "DECLARATION_ID": 1205003
    },
    {
      "DECLARATION_ID": 1205004
    },
    {
      "DECLARATION_ID": 1205005
    },
    {
      "DECLARATION_ID": 1205006
    },
    {
      "DECLARATION_ID": 1205046
    },
    {
      "DECLARATION_ID": 1205132
    },
    {
      "DECLARATION_ID": 1205133
    },
    {
      "DECLARATION_ID": 1205153
    },
    {
      "DECLARATION_ID": 1205154
    },
    {
      "DECLARATION_ID": 1205155
    },
    {
      "DECLARATION_ID": 1205156
    },
    {
      "DECLARATION_ID": 1205157
    },
    {
      "DECLARATION_ID": 1205204
    },
    {
      "DECLARATION_ID": 1205205
    },
    {
      "DECLARATION_ID": 1205206
    },
    {
      "DECLARATION_ID": 1205207
    },
    {
      "DECLARATION_ID": 1205248
    },
    {
      "DECLARATION_ID": 1205250
    },
    {
      "DECLARATION_ID": 1205251
    },
    {
      "DECLARATION_ID": 1205252
    },
    {
      "DECLARATION_ID": 1205253
    },
    {
      "DECLARATION_ID": 1205254
    },
    {
      "DECLARATION_ID": 1205277
    },
    {
      "DECLARATION_ID": 1205278
    },
    {
      "DECLARATION_ID": 1205282
    },
    {
      "DECLARATION_ID": 1205283
    },
    {
      "DECLARATION_ID": 1205303
    },
    {
      "DECLARATION_ID": 1205304
    },
    {
      "DECLARATION_ID": 1205305
    },
    {
      "DECLARATION_ID": 1205307
    },
    {
      "DECLARATION_ID": 1205325
    },
    {
      "DECLARATION_ID": 1205623
    },
    {
      "DECLARATION_ID": 1205624
    },
    {
      "DECLARATION_ID": 1205625
    },
    {
      "DECLARATION_ID": 1205626
    },
    {
      "DECLARATION_ID": 1205760
    },
    {
      "DECLARATION_ID": 1205761
    },
    {
      "DECLARATION_ID": 1205762
    },
    {
      "DECLARATION_ID": 1205795
    },
    {
      "DECLARATION_ID": 1205797
    },
    {
      "DECLARATION_ID": 1205798
    },
    {
      "DECLARATION_ID": 1205799
    },
    {
      "DECLARATION_ID": 1205801
    },
    {
      "DECLARATION_ID": 1205822
    },
    {
      "DECLARATION_ID": 1205823
    },
    {
      "DECLARATION_ID": 1205824
    },
    {
      "DECLARATION_ID": 1205825
    },
    {
      "DECLARATION_ID": 1205826
    },
    {
      "DECLARATION_ID": 1205827
    },
    {
      "DECLARATION_ID": 1205862
    },
    {
      "DECLARATION_ID": 1205863
    },
    {
      "DECLARATION_ID": 1205865
    },
    {
      "DECLARATION_ID": 1205866
    },
    {
      "DECLARATION_ID": 1205867
    },
    {
      "DECLARATION_ID": 1205868
    },
    {
      "DECLARATION_ID": 1205869
    },
    {
      "DECLARATION_ID": 1205870
    },
    {
      "DECLARATION_ID": 1205887
    },
    {
      "DECLARATION_ID": 1205888
    },
    {
      "DECLARATION_ID": 1205889
    },
    {
      "DECLARATION_ID": 1205890
    },
    {
      "DECLARATION_ID": 1205891
    },
    {
      "DECLARATION_ID": 1205892
    },
    {
      "DECLARATION_ID": 1205893
    },
    {
      "DECLARATION_ID": 1205894
    },
    {
      "DECLARATION_ID": 1205919
    },
    {
      "DECLARATION_ID": 1205920
    },
    {
      "DECLARATION_ID": 1205921
    },
    {
      "DECLARATION_ID": 1205922
    },
    {
      "DECLARATION_ID": 1205935
    },
    {
      "DECLARATION_ID": 1205936
    },
    {
      "DECLARATION_ID": 1205937
    },
    {
      "DECLARATION_ID": 1205938
    },
    {
      "DECLARATION_ID": 1205939
    },
    {
      "DECLARATION_ID": 1205942
    },
    {
      "DECLARATION_ID": 1205943
    },
    {
      "DECLARATION_ID": 1205945
    },
    {
      "DECLARATION_ID": 1205948
    },
    {
      "DECLARATION_ID": 1205949
    },
    {
      "DECLARATION_ID": 1206005
    },
    {
      "DECLARATION_ID": 1206073
    },
    {
      "DECLARATION_ID": 1206074
    },
    {
      "DECLARATION_ID": 1206075
    },
    {
      "DECLARATION_ID": 1206076
    },
    {
      "DECLARATION_ID": 1206077
    },
    {
      "DECLARATION_ID": 1206078
    },
    {
      "DECLARATION_ID": 1206110
    },
    {
      "DECLARATION_ID": 1206111
    },
    {
      "DECLARATION_ID": 1206112
    },
    {
      "DECLARATION_ID": 1206114
    },
    {
      "DECLARATION_ID": 1206134
    },
    {
      "DECLARATION_ID": 1206135
    },
    {
      "DECLARATION_ID": 1206136
    },
    {
      "DECLARATION_ID": 1206137
    },
    {
      "DECLARATION_ID": 1206138
    },
    {
      "DECLARATION_ID": 1206139
    }
  ]
}